sqla_filters/parser/json/__init__.py
sqla_filters/parser/json/exceptions.py
sqla_filters/parser/json/parser.py
sqla_filters_json-0.0.1.dist-info/LICENSE
sqla_filters_json-0.0.1.dist-info/METADATA
sqla_filters_json-0.0.1.dist-info/WHEEL
sqla_filters_json-0.0.1.dist-info/top_level.txt
sqla_filters_json-0.0.1.dist-info/RECORD
