Metadata-Version: 2.1
Name: sqla-filters-json
Version: 0.0.1
Summary: JSON parser for sqla-filters.
Home-page: https://github.com/MarcAureleCoste/sqla-filters-json
Author: Marc-Aurele Coste
License: MIT
Platform: UNKNOWN
Classifier: License :: OSI Approved :: MIT License
Classifier: Operating System :: OS Independent
Classifier: Programming Language :: Python
Classifier: Programming Language :: Python :: 3
Classifier: Programming Language :: Python :: 3.6
Classifier: Programming Language :: Python :: 3.7
Classifier: Programming Language :: Python :: 3 :: Only
Classifier: Topic :: Software Development :: Libraries :: Python Modules
Requires-Dist: sqla-filters (==0.0.2)
Provides-Extra: dev
Requires-Dist: pylint; extra == 'dev'
Requires-Dist: pep8; extra == 'dev'
Requires-Dist: autopep8; extra == 'dev'
Requires-Dist: ipython; extra == 'dev'
Requires-Dist: mypy; extra == 'dev'
Requires-Dist: pytest; extra == 'dev'
Requires-Dist: rope; extra == 'dev'
Requires-Dist: sphinx; extra == 'dev'
Requires-Dist: twine; extra == 'dev'
